pycountant/__init__.py
pycountant/data/__init__.py
pycountant/data/currency.py
pycountant/extra_types/__init__.py
pycountant/extra_types/number.py
pycountant/extra_types/provider.py
pycountant/models/__init__.py
pycountant/models/currency.py
pycountant/services/__init__.py
pycountant/services/fx.py
pycountant/services/tax.py
pycountant-0.2.2.dist-info/licenses/LICENSE
pycountant-0.2.2.dist-info/METADATA
pycountant-0.2.2.dist-info/WHEEL
pycountant-0.2.2.dist-info/top_level.txt
pycountant-0.2.2.dist-info/RECORD
